Workbook
Name _Account_Lookup: 'Account Table'!$E$1:$E$500

Sheet Cover
A1: ='Yardi Report'!A1
A2: Date | B2: 45900
A5: G/L Description | B5: Amount | C5: Reconciled? | D5: Notes
A6: Pre-Paid Insurance | B6: {=INDIRECT("'"&A6&"'!G5")} | C6: {=IF(INDIRECT("'"&A6&"'!H5")="","Yes",INDIRECT("'"&A6&"'!H5"))}
A7: Pre-Paid Association Fees | B7: {=INDIRECT("'"&A7&"'!G5")} | C7: {=IF(INDIRECT("'"&A7&"'!H5")="","Yes",INDIRECT("'"&A7&"'!H5"))}
A8: Pre-Paid Expenses - Other | B8: {=INDIRECT("'"&A8&"'!G5")} | C8: {=IF(INDIRECT("'"&A8&"'!H5")="","Yes",INDIRECT("'"&A8&"'!H5"))}
A9: Real Estate Tax Accrual | B9: {=INDIRECT("'"&A9&"'!G5")} | C9: {=IF(INDIRECT("'"&A9&"'!H5")="","Yes",INDIRECT("'"&A9&"'!H5"))}
A10: Sales Tax Collected | B10: {=INDIRECT("'"&A10&"'!G5")} | C10: {=IF(INDIRECT("'"&A10&"'!H5")="","Yes",INDIRECT("'"&A10&"'!H5"))}
A11: Sales Tax Payable | B11: {=INDIRECT("'"&A11&"'!G5")} | C11: {=IF(INDIRECT("'"&A11&"'!H5")="","Yes",INDIRECT("'"&A11&"'!H5"))}
A12: Interest Accrual | B12: {=INDIRECT("'"&A12&"'!G5")} | C12: {=IF(INDIRECT("'"&A12&"'!H5")="","Yes",INDIRECT("'"&A12&"'!H5"))}
A13: Expense Accrual | B13: {=INDIRECT("'"&A13&"'!G5")} | C13: {=IF(INDIRECT("'"&A13&"'!H5")="","Yes",INDIRECT("'"&A13&"'!H5"))}
A19: Completed by: | B19: RM
A20: Date Completed: | B20: 45944

Sheet Pre-Paid Insurance
A1: =Cover!A1
A2: =Cover!B2
A3: 1350-0001 Pre-Paid Insurance
E5: Account Balance | G5: =INDEX('Yardi Report'!A:E,MATCH(LEFT(A3,9),'Yardi Report'!A:A,0),3) | H5: =IF(G49=0,"","Out of Balance")
B7: Date | C7: Period | E7: G/L Description | G7: Amount | H7: Notes
J8: 760.58
B9: 45715 | C9: =B9 | E9: Storable Insurance payment | F9: 32024.01
B10: 45747 | C10: =B10 | E10: Expense Distribution | F10: -2668.67
B11: 45777 | C11: =B11 | E11: Expense Distribution | F11: -2668.67
B12: 45808 | C12: 45778 | E12: Expense Distribution | F12: -2668.67
B13: 45838 | C13: 45809 | E13: Expense Distribution | F13: -2668.67
B14: 45869 | C14: 45839 | E14: Expense Distribution | F14: -2668.67
B15: 45897 | C15: 45870 | E15: Expense Distribution | F15: -2668.67
B16: 45929 | C16: 45901 | E16: Expense Distribution | F16: -2668.67
E17: Expense Distribution | F17: 0
E18: Expense Distribution | F18: 0
E19: Expense Distribution | F19: 0
E20: Expense Distribution | F20: 0
E21: Expense Distribution | F21: 0
E22: Left to Distribute | G22: =SUM(F9:F21)
B24: 45747 | C24: =B24 | E24: PFG Insurance | F24: 24353.23 | H24: Endorsement
B25: 45747 | C25: =B25 | E25: Expense Distribution | F25: -2029.44
B26: 45777 | C26: =B26 | E26: Expense Distribution | F26: -2029.44
B27: 45808 | C27: 45778 | E27: Expense Distribution | F27: -2029.44
B28: 45808 | C28: 45778 | D28: Insurance Reimbursement | F28: -326.7
B29: 45838 | C29: 45809 | E29: Expense Distribution | F29: -2029.44
B30: 45869 | C30: 45839 | E30: Expense Distribution | F30: -2029.44
B31: 45897 | C31: 45870 | E31: Expense Distribution | F31: -2029.44
B32: 45929 | C32: 45901 | E32: Expense Distribution | F32: -2029.44
E33: Expense Distribution | F33: 0
E34: Expense Distribution | F34: 0
E35: Expense Distribution | F35: 0
E36: Expense Distribution | F36: 0
E37: Expense Distribution | F37: 0
E39: Left to Distribute | G39: =SUM(F24:F37)
E43: P1 Finance Holding | G43: 18401.72
E44: Venice Insurance Reimbursment | G44: 2965.68
B45: 45894 | C45: 45870 | E45: Property First G | G45: 8283.25
B46: 45900 | C46: 45870 | E46: Property First G | G46: 938.5
E49: Variance | G49: =ROUND(G5-SUM(G9:G48),2) | H49: =IF(G49=0,"","Out of Balance")

Sheet Pre-Paid Association Fees
A1: =Cover!A1
A2: =Cover!B2
A3: 1350-0002 Pre-Paid Association Fees
E5: Account Balance | G5: =INDEX('Yardi Report'!A:E,MATCH(LEFT(A3,9),'Yardi Report'!A:A,0),3) | H5: =IF(G25=0,"","Out of Balance")
B7: Date | C7: Period | E7: G/L Description | G7: Amount | H7: Notes
B9: 45730 | C9: =B9 | E9: Warm Springs Commercial Property Owners Association Inc 2025 Assoc dues | F9: 2766
B10: 45684 | C10: =B10 | E10: Expense Distribution | F10: -230.5
B11: 45716 | C11: =B11 | E11: Expense Distribution | F11: -230.5
B12: 45747 | C12: =B12 | E12: Expense Distribution | F12: -230.5
B13: 45777 | C13: =B13 | E13: Expense Distribution | F13: -230.5
B14: 45808 | C14: =B14 | E14: Expense Distribution | F14: -230.5
B15: 45838 | C15: 45809 | E15: Expense Distribution | F15: -230.5
B16: 45869 | C16: 45839 | E16: Expense Distribution | F16: -230.5
B17: 45900 | C17: 45870 | E17: Expense Distribution | F17: -230.5
B18: 45929 | C18: 45901 | E18: Expense Distribution | F18: -230.5
E19: Expense Distribution
E20: Expense Distribution
E21: Expense Distribution
E22: Left to Distribute | G22: =SUM(F9:F21)
E25: Variance | G25: =ROUND(G5-SUM(G9:G24),2) | H25: =IF(G25=0,"","Out of Balance")

Sheet Pre-Paid Expenses - Other
A1: =Cover!A1
A2: =Cover!B2
A3: 1350-9000 Pre-Paid Expenses - Other
E5: Account Balance | G5: =INDEX('Yardi Report'!A:E,MATCH(LEFT(A3,9),'Yardi Report'!A:A,0),3) | H5: =IF(G25=0,"","Out of Balance")
B7: Date | C7: Period | E7: G/L Description | G7: Amount | H7: Notes
B9: 45068
B10: 45017
B12: 45107
B13: 45137
B14: 45168
B15: 45199
B16: 45229
B17: 45260
B18: 45290
B19: 45321
B20: 45351
B21: 45381
E25: Variance | G25: =ROUND(G5-SUM(G9:G24),2) | H25: =IF(G25=0,"","Out of Balance")

Sheet Real Estate Tax Accrual
A1: =Cover!A1
A2: =Cover!B2
A3: 2305-0000 Real Estate Tax Accrual
E5: Account Balance | G5: =-INDEX('Yardi Report'!A:E,MATCH(LEFT(A3,9),'Yardi Report'!A:A,0),3) | H5: =IF(G61=0,"","Out of Balance")
B7: Date | E7: G/L Description | G7: Amount | H7: Notes
J8: 760.58
B9: 44978 | C9: 44958 | E9: 2023 Ad Valorem Tax Proration | F9: -5432.57 | J9: =+J8*12
B10: 44978 | C10: 44958 | E10: 2023 Non-Ad Valorem Tax Proration | F10: 19.06
B11: 44985 | C11: 44958 | E11: 7 days RE Tax expense | F11: -731.29
B12: 45009 | C12: 44986 | E12: Monthly RE Tax accrual | F12: -3177.71
B13: 45041 | C13: 45017 | E13: Monthly RE Tax accrual | F13: -3177.71
B14: 45072 | C14: 45047 | E14: Monthly RE Tax accrual | F14: -3177.71
B15: 45103 | C15: 45078 | E15: Monthly RE Tax accrual | F15: -3177.71
B16: 45138 | C16: 45108 | E16: Monthly RE Tax accrual | F16: -3177.71
B17: 45163 | C17: 45139 | E17: Monthly RE Tax accrual | F17: -3177.71
B18: 45198 | C18: 45170 | E18: Monthly RE Tax accrual | F18: -3177.71
B19: 45226 | C19: 45200 | E19: Monthly RE Tax accrual | F19: -3177.71 | J19: 560.09
B20: 45260 | C20: 45231 | E20: Monthly RE Tax accrual | F20: -3177.71 | J20: =+J19*12
B21: 45287 | C21: 45261 | E21: Monthly RE Tax accrual | F21: -3177.71
B22: 45237 | C22: 45231 | E22: Tax Payment | F22: 44256.12
E23: Tax Payment
E24: (Over)/Under Accrual | G24: =SUM(F9:F23)
B26: 45322 | C26: 45292 | E26: Monthly Tax Accrual | F26: -5657.86
B27: 45348 | C27: 45323 | E27: Monthly Tax Accrual | F27: -5657.86
B28: 45376 | C28: 45352 | E28: Monthly Tax Accrual | F28: -5657.86
B29: 45412 | C29: 45383 | E29: Monthly Tax Accrual | F29: -5657.86
B30: 45439 | C30: 45413 | E30: Monthly Tax Accrual | F30: -5657.86
B31: 45471 | C31: 45444 | E31: Monthly Tax Accrual | F31: -5657.86
B32: 45502 | C32: 45474 | E32: Monthly Tax Accrual | F32: -5657.86
B33: 45533 | C33: 45505 | E33: Monthly Tax Accrual | F33: -5657.86
B34: 45562 | C34: 45536 | E34: Monthly Tax Accrual | F34: -5657.86
B35: 45593 | C35: 45566 | E35: Monthly Tax Accrual | F35: -5657.86
B36: 45625 | C36: =B36 | E36: Monthly Tax Accrual | F36: -5657.86
B37: 45657 | C37: =B37 | E37: Monthly Tax Accrual | F37: -5657.8
B38: 45616 | C38: =B38 | E38: Tax Payment | F38: 67894.26 | H38: Tax payment from escrow
E39: Tax Payment | F39: 0
E40: (Over)/Under Accrual | G40: =SUM(F26:F39)
B42: 45688 | C42: =B42 | E42: Monthly Tax Accrual | F42: -5827.6
B43: 45716 | C43: =B43 | E43: Monthly Tax Accrual | F43: -5827.6
B44: 45747 | C44: =B44 | E44: Monthly Tax Accrual | F44: -5827.6
B45: 45777 | C45: =B45 | E45: Monthly Tax Accrual | F45: -5827.6
B46: 45808 | C46: =B46 | E46: Monthly Tax Accrual | F46: -5827.6
B47: 45838 | C47: =B47 | E47: Monthly Tax Accrual | F47: -5827.6
B48: 45869 | C48: =B48 | E48: Monthly Tax Accrual | F48: -5827.6
B49: 45900 | C49: =B49 | E49: Monthly Tax Accrual | F49: -5827.6
B50: 45929 | C50: =B50 | E50: Monthly Tax Accrual | F50: -5827.6
E51: Monthly Tax Accrual | F51: 0
E52: Monthly Tax Accrual | F52: 0
E53: Monthly Tax Accrual | F53: 0
E54: Tax Payment | F54: 0
E55: Tax Payment | F55: 0
E56: (Over)/Under Accrual | G56: =SUM(F42:F55)
E61: Variance | G61: =ROUND(G5-SUM(G9:G60),2) | H61: =IF(G61=0,"","Out of Balance")

Sheet Sales Tax Collected
A1: =Cover!A1
A2: =Cover!B2
A3: 2310-0000 Sales Tax Collected
E5: Account Balance | G5: =-INDEX('Yardi Report'!A:E,MATCH(LEFT(A3,9),'Yardi Report'!A:A,0),3) | H5: =IF(G53=0,"","Out of Balance")
B7: Date | E7: G/L Description | G7: Amount | H7: Notes
J8: 760.58
B9: 45626 | C9: 45597 | E9: 11.2024 cc receipts | F9: -3322.8
B10: 45626 | C10: 45597 | E10: Tax Payment | F10: 3300.75
E11: (Over)/Under Accrued | G11: =+F10+F9
B13: 45657 | C13: =B13 | E13: 12.2024 cc receipts | F13: =-3360.31+22.05
B14: 45657 | C14: =B14 | E14: Tax Payment | F14: 3311.45
E15: (Over)/Under Accrued | G15: =+F14+F13
B17: 45688 | C17: =B17 | E17: 01.2025 cc receipts | F17: =-3626.3+48.86
B18: 45688 | C18: =B18 | E18: Tax Payment | F18: 3556.11
E19: (Over)/Under Accrued | G19: =F18+F17
B21: 45716 | C21: =B21 | E21: 02.2025 cc receipts | F21: =-3518+70.19
B22: 45716 | C22: =B22 | E22: Tax Payment | F22: 3418.59
E23: (Over)/Under Accrued | G23: =F22+F21
B25: 45747 | C25: =B25 | E25: 03.2025 cc receipts | F25: =-3800.78+99.41
B26: 45747 | C26: =B26 | E26: Tax Payment | F26: 3687.09
E27: (Over)/Under Accrued | G27: =F26+F25
B29: 45777 | C29: =B29 | E29: 04.2025 cc receipts | F29: =-3999.64+113.69
B30: 45777 | C30: =B30 | E30: Tax Payment | F30: 3853.96
E31: (Over)/Under Accrued | G31: =F30+F29
B33: 45808 | C33: 45778 | E33: 05.2025 cc receipts | F33: -4217
B34: 45808 | C34: 45778 | E34: Tax Payment | F34: 4190.01
E35: (Over)/Under Accrued | G35: =+F33+F34
B37: 45838 | C37: 45809 | E37: 06.2025 cc receipts | F37: -3563.92
B38: 45838 | C38: 45809 | E38: Tax Payment | F38: 3532.79
E39: (Over)/Under Accrued | G39: =+F37+F38
B41: 45869 | C41: 45839 | E41: 07.2025 cc receipts | F41: -4107.54
B42: 45869 | C42: 45839 | E42: Tax Payment | F42: 4076.19
E43: (Over)/Under Accrued | G43: =+F41+F42
B45: 45900 | C45: 45870 | E45: 08.2025 cc receipts | F45: -4321.04
B46: 45900 | C46: 45870 | E46: Tax Payment | F46: 4311.05
E47: (Over)/Under Accrued | G47: =+F45+F46
B49: 45900 | C49: 45870 | E49: 09.2025 cc receipts | F49: -3751.45
B50: 45900 | C50: 45870 | E50: Tax Payment | F50: 3715.57
E51: (Over)/Under Accrued | G51: =+F49+F50
E53: Variance | G53: =ROUND(G5-SUM(G9:G52),2) | H53: =IF(G53=0,"","Out of Balance")

Sheet Sales Tax Payable
A1: =Cover!A1
A2: =Cover!B2
A3: 2310-0001 Sales Tax Payable
E5: Account Balance | G5: =-INDEX('Yardi Report'!A:E,MATCH(LEFT(A3,9),'Yardi Report'!A:A,0),3) | H5: =IF(G39=0,"","Out of Balance")
B7: Date | E7: G/L Description | G7: Amount | H7: Notes
J8: 760.58
B9: 44985 | C9: 44958 | E9: Wildwood prorated sales tax EST | G9: -1177.1
B10: 45016 | C10: 44986 | E10: EST Sales Tax | G10: -3149.22
B11: 45046 | C11: 45017 | E11: EST Sales Tax | G11: -2982.79
B12: 45077 | C12: 45047 | E12: 7% of rent | G12: -3940.48
B13: 45107 | C13: 45078 | E13: Sales or Parking Tax Accrual | G13: -3088.11
B14: 45138 | C14: 45108 | E14: EST sales tax | G14: -3672.3
B15: 45169 | C15: 45139 | E15: FL Dept of Revenue | G15: 13031.19
B16: 45169 | C16: 45139 | E16: FL Dept of Revenue | G16: 9793.35
B17: 45169 | C17: 45139 | E17: FL Dept of Revenue | G17: 1056.08
B18: 45169 | C18: 45139 | E18: FL Dept of Revenue | G18: 377.85
B19: 45169 | C19: 45139 | E19: FL Dept of Revenue | G19: 37.79
B20: 45169 | C20: 45139 | E20: Sales/Parking Tax accrual and adj for collected Sales Tax | G20: -4035.25
... B27: 45378 | C27: 45352 | E27: Sales tax payable | G27: 1050.52
E39: Variance | G39: =ROUND(G5-SUM(G9:G36),2) | H39: =IF(G39=0,"","Out of Balance")

Sheet Interest Accrual
A1: =Cover!A1
A2: =Cover!B2
A3: 2609-0000 Interest Accrual
E5: Account Balance | G5: =-INDEX('Yardi Report'!A:E,MATCH(LEFT(A3,9),'Yardi Report'!A:A,0),3) | H5: =IF(G48=0,"","Out of Balance")
B7: Date | C7: Period | E7: G/L Description | G7: Amount | H7: Notes
J8: 760.58
B9: 44985 | C9: 44958 | E9: Add'l Feb accrual from April statement | F9: -1357.72
B10: 45016 | C10: 44986 | E10: March interest accrual | F10: -17417.9
B11: 45016 | C11: 44986 | E11: Add'l Mar accrual from April (1st) statement | F11: -7913.06
B12: 45046 | C12: 45017 | E12: Interest Accrual adjustment from April statement | F12: 25956.46
G13: =SUM(F9:F12)
B15: 45046 | C15: 45017 | E15: April Interest accrual (May 5 due date) | F15: -27810.6
B16: 45046 | C16: 45017 | E16: Adj April interest - incorrect calculation, daily interest was calculated to previous month | F16: 2468.89
B17: 45077 | C17: 45047 | E17: Adj interest for 3/20-4/19 - 5/5 payment for 3/20-4/19 | F17: 25539.11
G18: =SUM(F15:F17)
B20: 45077 | C20: 45047 | E20: Adj interest for 5/1-5/31 - 5/5 payment for 3/20-4/19 | F20: -26390.41
B21: 45107 | C21: 45078 | E21: Adj interest. 6/5 payment for 4/20-5/21 | F21: 27281.63
G22: =F21+F20
B24: 45107 | C24: 45078 | E24: Adj interest. 6/5 payment for 4/20-5/21 | F24: -25539.11
B25: 45138 | C25: 45108 | E25: Adj interest. 7/5 payment for 5/20-6/21 | F25: 26903.4
G26: =F25+F24
B28: 45138 | C28: 45108 | E28: Adj interest. 7/5 payment for 5/20-6/21 | F28: -26390.41 | J28: =+J8*12
B29: 45169 | C29: 45139 | E29: Adj interest. 8/5 payment for 6/20-7/20 | F29: 27670.52
G30: =F29+F28
B32: 45169 | C32: 45139 | E32: Adj interest. 8/5 payment for 6/20-7/20 | F32: -27670.52 | J32: 560.09
B33: 45199 | C33: 45170 | E33: Adj interest. 9/5 payment for 7/20-8/20 | F33: 28351.05 | J33: =+J32*12
G34: =F33+F32
B36: 45199 | C36: 45170 | E36: Adj interest. 9/5 payment for 7/20-8/20 | F36: -26777.92
B37: 45230 | C37: 45200 | E37: Adj interest. 10/5 payment for 8/20-9/20 | F37: 28351.05
G38: =F37+F36
B40: 45230 | C40: 45200 | E40: Adj interest. 10/5 payment for 8/20-9/20 | G40: -31325.81
B42: 45260 | C42: 45231 | E42: Adj for calendar days vs statement days | G42: 2581.28
B44: 45291 | C44: 45261 | E44: Adj interest expense to correct monthly expense | G44: -2944.97
B45: 45883 | C45: 45870 | E45: Closing fees and interest on loan mod 1710 | G45: 27302.81
E48: Variance | G48: =ROUND(G5-SUM(G9:G47),2) | H48: =IF(G48=0,"","Out of Balance")

Sheet Expense Accrual
A1: =Cover!A1
A2: =Cover!B2
A3: 2640-0998 Expense Accrual
E5: Account Balance | G5: =-INDEX('Yardi Report'!A:E,MATCH(LEFT(A3,9),'Yardi Report'!A:A,0),3) | H5: =IF(G157=0,"","Out of Balance")
B7: Date | C7: Period | E7: G/L Description | G7: Amount | H7: Notes
B9: 44985 | C9: 44958 | E9: Adj cc fees to correct month | F9: -60.13 | H9: Credit Card Processing Fees
B10: 44985 | C10: 44958 | E10: 10 days electric service per invoice | F10: -413.5 | H10: Electricity
B11: 44985 | C11: 44958 | E11: SiteLink accrual | F11: -263.61 | H11: Software
B12: 45016 | C12: 44986 | E12: EOM Expense Accruals for new property | F12: -1401.31 | H12: Electricity
B13: 45016 | C13: 44986 | E13: SiteLink accrual | F13: -203.48 | H13: Software
B14: 45016 | C14: 44986 | E14: duplicate payment to Spectrum | F14: 207.96 | H14: Telephone Service
B15: 45016 | C15: 44986 | E15: EOM Expense Accruals for new property | F15: -225 | H15: Trash Disposal
B16: 45016 | C16: 44986 | E16: Adj Trash accruals post invoicing | F16: 190 | H16: Trash Disposal
B17: 45046 | C17: 45017 | E17: EOM accruals - April fees | F17: -1154.97 | H17: Credit Card Processing Fees
B18: 45046 | C18: 45017 | E18: EOM accruals | F18: -1401.31 | H18: Electricity
B19: 45046 | C19: 45017 | E19: EOM accruals | F19: -60.13 | H19: Software
B20: 45046 | C20: 45017 | E20: SiteLink accrual | F20: -203.48 | H20: Software
... B59: 45282 | C59: 45261 | E59: Angela Cohen payment from SSSM | F59: -845 | H59: Payroll 1099 Contractor
B60: 45291 | C60: 45261 | E60: ck 3162023 - Theresa Reed | F60: -408.8
B61: 45291 | C61: 45261 | E61: ck 5192023 - Jim Lester | F61: -127.12
B62: 45272 | C62: 45261 | E62: CapOne additional .03 payment | F62: 0.03
E63: 2023 Total | G63: =SUM(F9:F62)
B64: 45322 | C64: 45292 | E64: EOM Accruals 01.31.2024 | F64: -300 | H64: Fire and Life Safety Maintenance
B65: 45322 | C65: 45292 | E65: EOM Accruals 01.31.2024 | F65: -600 | H65: Janiorial Services
B66: 45322 | C66: 45292 | E66: Angela Cohen 12.22 pd by SSSM | F66: 865 | H66: Payroll 1099 Contractor
B67: 45365 | C67: 45352 | E67: Expense Accrual : 01.2024 Google Ads | F67: 1112.64 | H67: Internet Marketing
B68: 45443 | C68: 45413 | E68: Communication Center_Accruals_05.31.2024 | F68: -221 | H68: Communication Center
B69: 45443 | C69: 45413 | E69: Electricity_Accruals_05.31.2024 | F69: -1208 | H69: Electricity
B70: 45504 | C70: 45474 | E70: Capital One Payment 06/2024_Duplicate | F70: 1866.6
B71: 45504 | C71: 45474 | E71: Capital One 07/2024 - SS Wildwood | F71: -628.6
B72: 45626 | C72: =B72 | E72: Capital One 11/2024 - SS Wildwood | F72: -3805.5
B73: 45657 | C73: =B73 | E73: Landscaping accrual | F73: 420 | H73: Landscaping
B74: 45657 | C74: =B74 | E74: Capital One 11/2024 - SS Wildwood | F74: 3806.66
E75: 2024 Total | G75: =SUM(F64:F74)
B79: 45716 | C79: 45689 | E79: 022025BankFeesSsofWildwood | G79: =-244.16-13.42 | H79: Bank Charges Expense
B81: 45777 | C81: 45748 | E81: April Accruals | G81: -717.84 | H81: Electrcity
B83: 45735 | C83: =B83 | E83: 03.2025 Google Ads (1) | G83: 2760.74 | H83: Internet Marketing
B84: 45777 | C84: 45748 | E84: May payment for 04/16-30/2025 Google Ads | G84: -3497.65 | H84: Internet Marketing
B85: 45808 | C85: 45778 | E85: 04.2025 Google Ads | G85: 3497.65 | H85: Internet Marketing
B86: 45808 | C86: 45778 | E86: June payment for 05.01-12.2025 Google Ads | G86: -2739.52 | H86: Internet Marketing
B87: 45808 | C87: 45778 | E87: June payment for 05.13-30.2025 Google Ads | G87: -6089.45 | H87: Internet Marketing
B88: 45838 | C88: 45809 | E88: 05.31-06.12.2025 Google Ads | G88: 4046.72 | H88: Internet Marketing
B89: 45838 | C89: 45809 | E89: July payment for 05.31-06.12.2025 Google Ads | G89: -4046.72 | H89: Internet Marketing
B90: 45838 | C90: 45809 | E90: July payment for 06.15-30.2025 Google Ads | G90: -5266.39 | H90: Internet Marketing
B91: 45869 | C91: 45839 | E91: 07.2025 Google Ads Payment 1 - Wildwood | G91: 5341.9 | H91: Internet Marketing
B92: 45869 | C92: 45839 | E92: August payment for 07.01-15.2025 Google Ads | G92: -5341.9 | H92: Internet Marketing
B93: 45869 | C93: 45839 | E93: August payment for 07.16-31.2025 Google Ads | G93: -6063.39 | H93: Internet Marketing
B94: 45891 | C94: 45870 | E94: 07.2025 Google Ads Payment 2 - Wildwood | G94: 3063.39 | H94: Internet Marketing
B95: 45891 | C95: 45870 | E95: 07.2025 Google Ads Payment 2 - Wildwood | G95: 3000 | H95: Internet Marketing
... B108: 45930 | C108: 45901 | E108: 082025 SpareFoot Fee | G108: 1310.4 | H108: Software
B111: 45747 | C111: =B111 | E111: Under accrued for 12.2024 expense | G111: -420 | H111: Landscapimg
B112: 45716 | C112: 45689 | E112: Landscaping accrual | G112: -920 | H112: Landscaping
B113: 45777 | C113: 45748 | E113: April Accruals | G113: -420 | H113: Landscaping
B114: 45808 | C114: 45778 | E114: Landscaping - May Accruals | G114: -420 | H114: Landscaping
B115: 45838 | C115: 45809 | E115: Landscaping - June Accruals | G115: -420 | H115: Landscaping
B116: 45869 | C116: 45839 | E116: Landscaping - July Accruals | G116: -420 | H116: Landscaping
B117: 45900 | C117: 45870 | E117: Landscaping - Aug Accruals | G117: -420 | H117: Landscaping
B118: 45930 | C118: 45901 | E118: Landscaping - September Accruals | G118: -420 | H118: Landscaping
B120: 45777 | C120: 45748 | E120: April Accruals | G120: -34.67 | H120: Trash
B122: 45777 | C122: 45748 | E122: April Accruals | G122: -80.04 | H122: Water and Sewer
B124: 45687 | C124: 45658 | E124: 01.2025 Cap One partial payment | G124: 59.67
B125: 45688 | C125: 45658 | E125: CApOne Payment 12/2024 | G125: 590.38
B126: 45688 | C126: 45658 | E126: CApOne Payment 01/2025 | G126: 1777.2
B127: 45688 | C127: 45658 | E127: Capital One 01/2025 - SS Wildwood | G127: -2739.16
B128: 45716 | C128: 45689 | E128: 01.2025 Capital One | G128: 311.91
B129: 45716 | C129: 45689 | E129: 01.2025 CapOne | G129: 122.42
B130: 45716 | C130: 45689 | E130: CapOne 02/2025 - SS Wildwood | G130: -755.73
B131: 45729 | C131: =B131 | E131: 02.2025 CapOne payment | G131: 633.3
B132: 45777 | C132: 45748 | E132: Capital One 04/2025 - SS Wildwood | G132: -1390.46
B133: 45808 | C133: 45778 | E133: 05.2025 CapOne partial payment | G133: 832.26
B134: 45808 | C134: 45778 | E134: Capital One 04/2025 - SS Wildwood | G134: 1390.46
B135: 45808 | C135: 45778 | E135: Capital One Payment 05/12/25 | G135: 2739.52
B136: 45808 | C136: 45778 | E136: Capital One 05/2025 - S Wildwood | G136: -2483.13
B137: 45838 | C137: 45809 | E137: CapOne payment for 05.2025 CapOne | G137: 1650.87
B138: 45838 | C138: 45809 | E138: Capital One Payment 05.2025 | G138: 6089.45
B139: 45838 | C139: 45809 | E139: Capital One 06/2025 - SS Wildwood | G139: -416.26
B140: 45869 | C140: 45839 | E140: CapOne payment for 06.2025 CapOne - SS Wildwood | G140: 416.26
B141: 45869 | C141: 45839 | E141: Capital One 06.2025 | G141: 5266.39
B142: 45869 | C142: 45839 | E142: Capital One 07/2025 - SS Vehicle | G142: -436.3
B143: 45874 | C143: 45870 | E143: Capital One 07.2025 | G143: 270.04
... B147: 45930 | C147: 45901 | E147: Capital One 09/2025 - SS Wildwood | G147: -674.28
B149: 45808 | C149: 45778 | E149: StoreEase Accrual | G149: -188 | H149: Communication center
B150: 45838 | C150: 45809 | E150: StoreEase Accrual | G150: -188 | H150: Communication center
B151: 45930 | C151: 45901 | E151: StoreEase Accrual | G151: -188 | H151: Communication center
B153: 45900 | C153: 45870 | E153: Chase Fee Accrual | G153: -250 | H153: Chase fee
B154: 45930 | C154: 45901 | E154: 08.2025 Chase Analysis Fees_SSofWildwood | G154: 299.28 | H154: Chase fee
E157: Variance | G157: =ROUND(G5-SUM(G9:G156),2) | H157: =IF(G157=0,"","Out of Balance")

Sheet Yardi Report
A1: Storsafe of Wildwood (sswildwo)
A2: Balance Sheet (With Period Change)
A3: Period = Jan 2025-Oct 2025
A4: Book = Accrual
C5: Balance | D5: Beginning | E5: Net
C6: Current Period | D6: Balance | E6: Change
A7: 1000-0000 | B7: ASSETS
A9: 1100-0000 | B9: CASH
A10: 1110-4954 | B10: SSWwd Chase | C10: -11726.93 | D10: -10912.37 | E10: -814.56
A11: 1110-4955 | B11: SSWwd Busey | C11: 86521.56 | D11: 5748.61 | E11: 80772.95
A12: 1190-0000 | B12: TOTAL CASH | C12: 74794.63 | D12: -5163.76 | E12: 79958.39
A14: 1200-0000 | B14: RESTRICTED CASH
A15: 1200-0001 | B15: Interest Reserve | C15: 100599.92 | D15: 337166.3 | E15: -236566.38
A16: 1200-0003 | B16: Escrow Reserve | C16: 62389.67 | D16: -14983.69 | E16: 77373.36
A17: 1200-0004 | B17: Escrow Construction | C17: 0 | D17: 988311.25 | E17: -988311.25
A18: 1200-0005 | B18: Utility Security Deposits | C18: 8293.31 | D18: 2000 | E18: 6293.31
A19: 1200-0010 | B19: Bank Held Funds Account | C19: 175000 | D19: 175000 | E19: 0
A20: 1250-0000 | B20: TOTAL RESTRICTED CASH | C20: 346282.9 | D20: 1487493.9 | E20: -1141211
A22: 1300-0000 | B22: Accounts Receivable | C22: 36784.55 | D22: 25529.78 | E22: 11254.77
A24: 1350-0000 | B24: Pre-Paid Expenses
A25: 1350-0001 | B25: Pre-Paid Insurance | C25: 49054.81 | D25: 5352.17 | E25: 43702.64
A26: 1350-0002 | B26: Pre-Paid Association Fees | C26: 461 | D26: 0 | E26: 461
A27: 1350-9000 | B27: Pre-Paid Expenses - Other | C27: 0 | D27: 143.84 | E27: -143.84
A28: 1350-9999 | B28: Total Pre-Paid Expenses | C28: 49515.81 | D28: 5496.01 | E28: 44019.8
A30: 1400-0000 | B30: PROPERTY
A31: 1410-0000 | B31: Land | C31: 914345.13 | D31: 914345.13 | E31: 0
A32: 1500-0010 | B32: Building Improvements | C32: 13435838 | D32: 13435838 | E32: 0
A33: 1500-0040 | B33: Loan Fees A | C33: 105225 | D33: 105225 | E33: 0
A34: 1500-0045 | B34: Loan Fees B | C34: 28650 | D34: 28650 | E34: 0
A35: 1500-0050 | B35: AD Building | C35: -388011 | D35: -388011 | E35: 0
A36: 1500-0085 | B36: A/A Loan Fees - A | C36: -49088 | D36: -49088 | E36: 0
A38: 1600-0000 | B38: CONSTRUCTION IN PROGRESS
A39: 1600-1000 | B39: Draws
A40: 1600-1015 | B40: Draw 15 | C40: 307068.3 | D40: 0 | E40: 307068.3
A41: 1600-1016 | B41: Draw 16 | C41: 596738.85 | D41: 0 | E41: 596738.85
A42: 1600-9999 | B42: TOTAL CONSTRUCTION IN PROGRESS | C42: 903807.15 | D42: 0 | E42: 903807.15
A43: 1890-0000 | B43: TOTAL PROPERTY | C43: 14950767 | D43: 14046959 | E43: 903807.15
A45: 1990-0000 | B45: TOTAL ASSETS | C45: 15458144 | D45: 15560315 | E45: -102170.85
A47: 2000-0000 | B47: LIABILITIES AND CAPITAL
A49: 2100-0000 | B49: LIABILITIES
A50: 2110-0000
A51: 2120-0000 | B51: Note 2 Principal | C51: 5338666.2 | D51: 5330000 | E51: 8666.15
A52: 2135-0020
A53: 2150-0007 | B53: Due To/From Elmdale Commercial | C53: 208000 | D53: 0 | E53: 208000
A54: 2150-0020 | B54: Due To/(From) Other Property | C54: -125710.31 | D54: -102919.47 | E54: -22790.84
A55: 2150-0022 | B55: Due To/(From) SSSM | C55: -19999.44 | D55: -18899.44 | E55: -1100
A56: 2200-0000 | B56: Accounts Payable | C56: 94290.62 | D56: 17209.08 | E56: 77081.54
A57: 2210-0000 | B57: Prepaid Rent | C57: 35597.13 | D57: 19332.03 | E57: 16265.1
A58: 2250-0000 | B58: Tenant Deposits | C58: 1050 | D58: 150 | E58: 900
A59: 2250-0010 | B59: Truck Rental Deposit | C59: 750 | D59: 150 | E59: 600
A61: 2300-0000 | B61: TAX LIABILITIES
A62: 2305-0000 | B62: Real Estate Tax Accrual | C62: 58275.78 | D62: -0.22 | E62: 58276
A63: 2310-0000 | B63: Sales Tax Collected | C63: 318.14 | D63: 48.86 | E63: 269.28
A64: 2310-0001
A65: 2490-0000 | B65: TOTAL TAX LIABILITIES | C65: 47525.4 | D65: -11019.88 | E65: 58545.28
A66: 2609-0000 | B66: Interest Accrual | C66: -867.77 | D66: 26435.04 | E66: -27302.81
A67: 2640-0998 | B67: Expense Accrual | C67: 6457.77 | D67: 6816.96 | E67: -359.19
A68: 2640-0999 | B68: Payroll Accrual | C68: 0 | D68: 455.69 | E68: -455.69
A69: 2990-0000 | B69: TOTAL LIABILITIES | C69: 9937176.6 | D69: 9703651 | E69: 233525.54
A71: 3000-0000 | B71: CAPITAL
A73: 3303-2151 | B73: Storsafe DRE JV Contribution | C73: 6645917 | D73: 6645917 | E73: 0
A74: 3303-2152
A75: 3303-2153 | B75: STORSAFE DRE JV TOTAL | C75: 6531587 | D75: 6531587 | E75: 0
A77: 3800-0000 | B77: Retained Earnings | C77: -1010619.1 | D77: -674922.75 | E77: -335696.39
A78: 3890-0000 | B78: TOTAL CAPITAL | C78: 5520967.9 | D78: 5856664.2 | E78: -335696.39
A80: 3990-0000

Sheet Chart of Accounts
A1: Chart of Accounts
A5: Account | B5: Account Name | C5: Normal | D5: Acct | E5: Rpt | G5: Line | H5: Offset | I5: Hold-For | J5: Accrual | K5: Total | L5: Flags
C6: Balance | D6: Type | E6: Type | F6: Margin | G6: Adv. | H6: Account | I6: Account | J6: Account | K6: Account
A7: 1000-0000 | B7: ASSETS | C7: Debit | D7: Head | E7: Bal | F7: 1 | G7: 1
A8: 1100-0000 | B8: CASH | C8: Debit | D8: Head | E8: Bal | F8: 1 | G8: 2
A9: 1100-0001 | B9: Cash Reserve | C9: Debit | D9: Reg | E9: Bal | F9: 1 | G9: 1 | L9: Cash
A10: 1100-0500 | B10: do not use | C10: Debit | D10: Reg | E10: Bal | F10: 1 | G10: 1 | K10: 1190-0000 | L10: Cash
A11: 1110-0000 | B11: BMO Harris | C11: Debit | D11: Reg | E11: Bal | F11: 1 | G11: 1 | K11: 1190-0000 | L11: Cash
A12: 1110-0001 | B12: BMO Harris Reserves 3839 | C12: Debit | D12: Reg | E12: Bal | F12: 1 | G12: 1 | K12: 1190-0000 | L12: Cash
A13: 1110-0002 | B13: Associated Bank - Operating | C13: Debit | D13: Reg | E13: Bal | F13: 1 | G13: 1 | K13: 1190-0000 | L13: Cash
A14: 1110-0003 | B14: 8211 Kilpatrick BB Checking | C14: Debit | D14: Reg | E14: Bal | F14: 1 | G14: 1 | K14: 1190-0000 | L14: Cash
A15: 1110-0004 | B15: 8211 Kilpatrick BB Savings | C15: Debit | D15: Reg | E15: Bal | F15: 1 | G15: 1 | K15: 1190-0000 | L15: Cash
A16: 1110-0005 | B16: 3830 Ashland Amal Checking | C16: Debit | D16: Reg | E16: Bal | F16: 1 | G16: 1 | K16: 1190-0000 | L16: Cash
A17: 1110-0006 | B17: 3830 Ashland Amal Savings | C17: Debit | D17: Reg | E17: Bal | F17: 1 | G17: 1 | K17: 1190-0000 | L17: Cash
A18: 1110-0010 | B18: Belmont Bank & Trust WC | C18: Debit | D18: Reg | E18: Bal | F18: 1 | G18: 1 | K18: 1190-0000 | L18: Cash
A19: 1110-0020 | B19: Belmont Bank and Trust Ruby Street | C19: Debit | D19: Reg | E19: Bal | F19: 1 | G19: 1 | K19: 1190-0000 | L19: Cash
A20: 1110-0030 | B20: Belmont Bank and Trust Indian Creek | C20: Debit | D20: Reg | E20: Bal | F20: 1 | G20: 1 | K20: 1190-0000 | L20: Cash
A21: 1110-0040 | B21: Belmont Bank and Trust Sherman Place | C21: Debit | D21: Reg | E21: Bal | F21: 1 | G21: 1 | K21: 1190-0000 | L21: Cash
... A135: 1110-4944 | B135: Palm Bay Key Bank | C135: Debit | D135: Reg | E135: Bal | F135: 1 | G135: 1 | K135: 1190-0000 | L135: Cash
A136: 1110-4945 | B136: Silver Springs Equitable Bank | C136: Debit | D136: Reg | E136: Inc | F136: 1 | G136: 1 | L136: ExclReg, Exclude
A137: 1110-4946 | B137: Silver Springs Equitable Bank | C137: Debit | D137: Reg | E137: Bal | F137: 1 | G137: 1 | K137: 1190-0000 | L137: Cash
A138: 1110-4947 | B138: Crown Point West Chase | C138: Debit | D138: Reg | E138: Bal | F138: 1 | G138: 1 | K138: 1190-0000 | L138: Cash
A139: 1110-4948 | B139: Merrillville South Chase | C139: Debit | D139: Reg | E139: Bal | F139: 1 | G139: 1 | K139: 1190-0000 | L139: Cash
A140: 1110-4949 | B140: SS of Palm Bay Busey Bank | C140: Debit | D140: Reg | E140: Bal | F140: 1 | G140: 1 | K140: 1190-0000 | L140: Cash
A141: 1110-4950 | B141: SS of Port Washington Chase | C141: Debit | D141: Reg | E141: Bal | F141: 1 | G141: 1 | K141: 1190-0000 | L141: Cash
A142: 1110-4951 | B142: MSS Chase | C142: Debit | D142: Reg | E142: Bal | F142: 1 | G142: 1 | K142: 1190-0000 | L142: Cash
A143: 1110-4952 | B143: CPSS Chase | C143: Debit | D143: Reg | E143: Bal | F143: 1 | G143: 1 | K143: 1190-0000 | L143: Cash
A144: 1110-4953 | B144: NFSS Chase | C144: Debit | D144: Reg | E144: Bal | F144: 1 | G144: 1 | K144: 1190-0000 | L144: Cash
A145: 1110-4954 | B145: SSWwd Chase | C145: Debit | D145: Reg | E145: Bal | F145: 1 | G145: 1 | K145: 1190-0000 | L145: Cash
A146: 1110-4955 | B146: SSWwd Busey | C146: Debit | D146: Reg | E146: Bal | F146: 1 | G146: 1 | K146: 1190-0000 | L146: Cash
A147: 1110-4957 | B147: Crown Point West Centier Operating | C147: Debit | D147: Reg | E147: Bal | F147: 1 | G147: 1 | K147: 1190-0000 | L147: Cash
A148: 1110-4958 | B148: Rockledge Centier Money Market | C148: Debit | D148: Reg | E148: Bal | F148: 1 | G148: 1 | K148: 1190-0000 | L148: Cash
... A188: 1140-0000 | B188: Association Reserve Account | C188: Debit | D188: Reg | E188: Bal | F188: 1 | G188: 1 | K188: 1190-0000 | L188: Cash
A189: 1140-8521 | B189: 21.8521 Association Reserve Account | C189: Debit | D189: Reg | E189: Inc | F189: 0 | G189: 1 | L189: Cash
A190: 1150-0000 | B190: Rent to RDG | C190: Debit | D190: Reg | E190: Bal | F190: 1 | G190: 1 | L190: Cash
A191: 1160-0000 | B191: Deposits to RDG | C191: Debit | D191: Reg | E191: Bal | F191: 1 | G191: 1 | L191: Cash
A192: 1170-0000 | B192: Transfers to RDG | C192: Debit | D192: Reg | E192: Bal | F192: 1 | G192: 1 | L192: Cash
A193: 1180-0000 | B193: Funds To From Martin & Marbry | C193: Debit | D193: Reg | E193: Bal | F193: 1 | G193: 1 | K193: 2990-0000 | L193: Cash, ExclReg
A194: 1190-0000 | B194: TOTAL CASH | C194: Debit | D194: Tot | E194: Bal | F194: 2 | G194: 1 | K194: 1990-0000
A195: 1190-0020 | B195: American Eagle Bank | C195: Debit | D195: Reg | E195: Bal | F195: 1 | G195: 1 | K195: 1190-0000 | L195: Cash
A196: 1200-0000 | B196: RESTRICTED CASH | C196: Debit | D196: Head | E196: Bal | F196: 1 | G196: 2 | K196: 1250-0000
A197: 1200-0001 | B197: Interest Reserve | C197: Debit | D197: Reg | E197: Bal | F197: 2 | G197: 1 | K197: 1250-0000 | L197: Cash Flow
A198: 1200-0002 | B198: Insurance & RET Reserves | C198: Debit | D198: Reg | E198: Bal | F198: 2 | G198: 1 | K198: 1250-0000 | L198: Cash Flow
A199: 1200-0003 | B199: Escrow Reserve | C199: Debit | D199: Reg | E199: Bal | F199: 2 | G199: 1 | K199: 1250-0000 | L199: Cash Flow
A200: 1200-0004 | B200: Escrow Construction | C200: Debit | D200: Reg | E200: Bal | F200: 2 | G200: 1 | K200: 1250-0000 | L200: Cash Flow
A201: 1200-0005 | B201: Utility Security Deposits | C201: Debit | D201: Reg | E201: Bal | F201: 2 | G201: 1 | K201: 1250-0000 | L201: Cash Flow
A202: 1200-0006 | B202: Crown Point West Centier | C202: Debit | D202: Reg | E202: Bal | F202: 2 | G202: 1 | K202: 1250-0000 | L202: Cash
A203: 1200-0007 | B203: HSS FBC Pledged DDA | C203: Debit | D203: Reg | E203: Bal | F203: 2 | G203: 1 | K203: 1250-0000 | L203: Cash
A204: 1200-0008 | B204: SS of Crown Point West Held | C204: Debit | D204: Reg | E204: Bal | F204: 2 | G204: 1 | K204: 1250-0000 | L204: Cash
A205: 1200-0009 | B205: 2201 3rd Party Operating Account | C205: Debit | D205: Reg | E205: Bal | F205: 2 | G205: 1 | K205: 1250-0000 | L205: Cash
A206: 1250-0000 | B206: TOTAL RESTRICTED CASH | C206: Debit | D206: Tot | E206: Bal | F206: 2 | G206: 1 | K206: 1990-0000
A207: 1300-0000 | B207: Accounts Receivable | C207: Debit | D207: Reg | E207: Bal | F207: 1 | G207: 2 | K207: 1990-0000 | L207: Cash Flow, AR
A208: 1350-0000 | B208: Pre-Paid Expenses | C208: Debit | D208: Head | E208: Bal | F208: 1 | G208: 2 | K208: 1350-9999
A209: 1350-0001 | B209: Pre-Paid Insurance | C209: Debit | D209: Reg | E209: Bal | F209: 1 | G209: 1 | K209: 1350-9999 | L209: Cash Flow
A210: 1350-0002 | B210: Pre-Paid Association Fees | C210: Debit | D210: Reg | E210: Bal | F210: 1 | G210: 1 | K210: 1350-9999 | L210: Cash Flow
A211: 1350-9000 | B211: Pre-Paid Expenses - Other | C211: Debit | D211: Reg | E211: Bal | F211: 1 | G211: 1 | K211: 1350-9999 | L211: Cash Flow
A212: 1350-9999 | B212: Total Pre-Paid Expenses | C212: Debit | D212: Tot | E212: Bal | F212: 2 | G212: 1 | K212: 1990-0000
A213: 1400-0000 | B213: PROPERTY | C213: Debit | D213: Head | E213: Bal | F213: 1 | G213: 2 | K213: 1890-0000
A214: 1401-0000 | B214: Property | C214: Debit | D214: Reg | E214: Bal | F214: 1 | G214: 1 | K214: 1890-0000 | L214: Cash Flow
A215: 1401-0001 | B215: Single Family Home | C215: Debit | D215: Reg | E215: Bal | F215: 1 | G215: 1 | K215: 1890-0000 | L215: Cash Flow
A216: 1401-0002 | B216: Condo | C216: Debit | D216: Reg | E216: Bal | F216: 1 | G216: 1 | K216: 1890-0000 | L216: Cash Flow
A217: 1401-0003 | B217: Commercial Building | C217: Debit | D217: Reg | E217: Bal | F217: 1 | G217: 1 | K217: 1890-0000 | L217: Cash Flow
A218: 1401-0004 | B218: MASS Units | C218: Debit | D218: Reg | E218: Bal | F218: 1 | G218: 1 | K218: 1890-0000 | L218: Cash Flow
A219: 1401-0100 | B219: Funds Held For Closing | C219: Debit | D219: Reg | E219: Bal | F219: 1 | G219: 1 | K219: 1890-0000 | L219: Cash Flow
A220: 1401-1000 | B220: Auction Funds | C220: Debit | D220: Reg | E220: Bal | F220: 1 | G220: 1 | K220: 1890-0000 | L220: Cash Flow
A221: 1410-0000 | B221: Land | C221: Debit | D221: Reg | E221: Bal | F221: 1 | G221: 1 | K221: 1890-0000 | L221: Cash Flow
A222: 1410-0001 | B222: Land 754 Adj | C222: Debit | D222: Reg | E222: Bal | F222: 1 | G222: 1 | K222: 1890-0000 | L222: Cash Flow
A223: 1410-1000 | B223: Investment in 1341 Foster | C223: Debit | D223: Reg | E223: Bal | F223: 1 | G223: 1 | K223: 1890-0000 | L223: Cash Flow
A224: 1411-0000 | B224: Inv Holdings 1602 Darrow | C224: Debit | D224: Reg | E224: Bal | F224: 1 | G224: 1 | K224: 1890-0000 | L224: Cash Flow
A225: 1412-0000 | B225: Inv Holdings 5408 63rd Street | C225: Debit | D225: Reg | E225: Bal | F225: 1 | G225: 1 | K225: 1890-0000 | L225: Cash Flow
... A265: 1500-0095 | B265: A/A Organization Costs | C265: Debit | D265: Reg | E265: Bal | F265: 1 | G265: 1 | K265: 1890-0000 | L265: Cash Flow
A266: 1600-0000 | B266: CONSTRUCTION IN PROGRESS | C266: Debit | D266: Head | E266: Bal | F266: 1 | G266: 2 | K266: 1600-9999
A267: 1600-0001 | B267: General Conditions | C267: Debit | D267: Reg | E267: Bal | F267: 1 | G267: 1 | K267: 1600-9999 | L267: Cash Flow
A268: 1600-0002 | B268: Overhead & Profit | C268: Debit | D268: Reg | E268: Bal | F268: 1 | G268: 1 | K268: 1600-9999 | L268: Cash Flow
A269: 1600-0003 | B269: Carpentry & Finishes | C269: Debit | D269: Reg | E269: Bal | F269: 1 | G269: 1 | K269: 1600-9999 | L269: Cash Flow
A270: 1600-0004 | B270: Cabinetry | C270: Debit | D270: Reg | E270: Bal | F270: 1 | G270: 1 | K270: 1600-9999 | L270: Cash Flow
A271: 1600-0005 | B271: Permits | C271: Debit | D271: Reg | E271: Bal | F271: 1 | G271: 1 | K271: 1600-9999 | L271: Cash Flow
A272: 1600-0006 | B272: Electrical | C272: Debit | D272: Reg | E272: Bal | F272: 1 | G272: 1 | K272: 1600-9999 | L272: Cash Flow
A273: 1600-0007 | B273: Plumbing | C273: Debit | D273: Reg | E273: Bal | F273: 1 | G273: 1 | K273: 1600-9999 | L273: Cash Flow
A274: 1600-0008 | B274: Demolition | C274: Debit | D274: Reg | E274: Bal | F274: 1 | G274: 1 | K274: 1600-9999 | L274: Cash Flow
A275: 1600-0009 | B275: Electric | C275: Debit | D275: Reg | E275: Bal | F275: 1 | G275: 1 | K275: 1600-9999 | L275: Cash Flow
A276: 1600-0010 | B276: Masonry | C276: Debit | D276: Reg | E276: Bal | F276: 1 | G276: 1 | K276: 1600-9999 | L276: Cash Flow
A277: 1600-0011 | B277: Roof | C277: Debit | D277: Reg | E277: Bal | F277: 1 | G277: 1 | K277: 1600-9999 | L277: Cash Flow
A278: 1600-0012 | B278: Elevator | C278: Debit | D278: Reg | E278: Bal | F278: 1 | G278: 1 | K278: 1600-9999 | L278: Cash Flow
... A281: 1600-0016 | B281: Sandblasting | C281: Debit | D281: Reg | E281: Bal | F281: 1 | G281: 1 | K281: 1600-9999 | L281: Cash Flow
A282: 1600-0017 | B282: Pre-Fabricated Buildings | C282: Debit | D282: Reg | E282: Bal | F282: 0 | G282: 1 | L282: Cash Flow
A283: 1600-0020 | B283: Engineering | C283: Debit | D283: Reg | E283: Bal | F283: 1 | G283: 1 | K283: 1600-9999 | L283: Cash Flow
A284: 1600-0024 | B284: Lender's Architectural Inspection Fee | C284: Debit | D284: Reg | E284: Bal | F284: 1 | G284: 1 | K284: 1600-9999 | L284: Cash Flow
A285: 1600-0025 | B285: Steel-Stairs, Railings and Ornamental | C285: Debit | D285: Reg | E285: Bal | F285: 1 | G285: 1 | K285: 1600-9999 | L285: Cash Flow
A286: 1600-0026 | B286: Fire Suppression | C286: Debit | D286: Reg | E286: Bal | F286: 1 | G286: 1 | K286: 1600-9999 | L286: Cash Flow
A287: 1600-0027 | B287: Fire Alarms | C287: Debit | D287: Reg | E287: Bal | F287: 1 | G287: 1 | K287: 1600-9999 | L287: Cash Flow
A288: 1600-0028 | B288: Storefront Systems & Exterior Doors/Windows | C288: Debit | D288: Reg | E288: Bal | F288: 1 | G288: 1 | K288: 1600-9999 | L288: Cash Flow, WIP
A289: 1600-0030 | B289: Concrete | C289: Debit | D289: Reg | E289: Bal | F289: 1 | G289: 1 | K289: 1600-9999 | L289: Cash Flow
A290: 1600-0035 | B290: Architect | C290: Debit | D290: Reg | E290: Bal | F290: 1 | G290: 1 | K290: 1600-9999 | L290: Cash Flow
A291: 1600-0036 | B291: Insurance | C291: Debit | D291: Reg | E291: Bal | F291: 1 | G291: 1 | K291: 1600-9999 | L291: Cash Flow
A292: 1600-0037 | B292: Soft Costs | C292: Debit | D292: Reg | E292: Bal | F292: 0 | G292: 1 | L292: Cash Flow
A293: 1600-0038 | B293: Resident Relocation | C293: Debit | D293: Reg | E293: Bal | F293: 0 | G293: 1 | K293: 1600-9999 | L293: Cash Flow
A294: 1600-0040 | B294: TENANT BUILDOUTS | C294: Debit | D294: Head | E294: Bal | F294: 1 | G294: 1 | K294: 1600-9999 | L294: Exclude
A295: 1600-0041 | B295: 314-LL W | C295: Debit | D295: Reg | E295: Bal | F295: 1 | G295: 1 | K295: 1600-9999 | L295: Cash Flow
A296: 1600-0042 | B296: 314-LL E | C296: Debit | D296: Reg | E296: Bal | F296: 1 | G296: 1 | K296: 1600-9999 | L296: Cash Flow
...

Sheet Account Table
A1: =IF(ISNA(INDEX('Yardi Report'!$A:$E,MATCH('Chart of Accounts'!$A7,'Yardi Report'!$A:$A,0),1)),"",INDEX('Yardi Report'!$A:$E,MATCH('Chart of Accounts'!$A7,'Yardi Report'!$A:$A,0),1)) | B1: =IF(ISNA(INDEX('Yardi Report'!$A:$E,MATCH('Chart of Accounts'!$A7,'Yardi Report'!$A:$A,0),2)),"",INDEX('Yardi Report'!$A:$E,MATCH('Chart of Accounts'!$A7,'Yardi Report'!$A:$A,0),2)) | C1: =IF(A1="","",1) | E1: =A1&" "&B1 | G1: 1 | H1: =IF(ISNA(INDEX(C1:E500,MATCH(G1,C1:C500,0),3)),"",INDEX(C1:E500,MATCH(G1,C1:C500,0),3))
A2: =IF(ISNA(INDEX('Yardi Report'!$A:$E,MATCH('Chart of Accounts'!$A8,'Yardi Report'!$A:$A,0),1)),"",INDEX('Yardi Report'!$A:$E,MATCH('Chart of Accounts'!$A8,'Yardi Report'!$A:$A,0),1)) | B2: =IF(ISNA(INDEX('Yardi Report'!$A:$E,MATCH('Chart of Accounts'!$A8,'Yardi Report'!$A:$A,0),2)),"",INDEX('Yardi Report'!$A:$E,MATCH('Chart of Accounts'!$A8,'Yardi Report'!$A:$A,0),2)) | C2: =IF(A2="","",C1+1) | E2: =A2&" "&B2 | G2: =+G1+1 | H2: =IF(ISNA(INDEX(C2:E501,MATCH(G2,C2:C501,0),3)),"",INDEX(C2:E501,MATCH(G2,C2:C501,0),3))
A3: =IF(ISNA(INDEX('Yardi Report'!$A:$E,MATCH('Chart of Accounts'!$A9,'Yardi Report'!$A:$A,0),1)),"",INDEX('Yardi Report'!$A:$E,MATCH('Chart of Accounts'!$A9,'Yardi Report'!$A:$A,0),1)) | B3: =IF(ISNA(INDEX('Yardi Report'!$A:$E,MATCH('Chart of Accounts'!$A9,'Yardi Report'!$A:$A,0),2)),"",INDEX('Yardi Report'!$A:$E,MATCH('Chart of Accounts'!$A9,'Yardi Report'!$A:$A,0),2)) | C3: =IF(A3="","",MAX($C$1:C2)+1) | E3: =A3&" "&B3 | G3: =+G2+1 | H3: =IF(ISNA(INDEX(C3:E502,MATCH(G3,C3:C502,0),3)),"",INDEX(C3:E502,MATCH(G3,C3:C502,0),3))
A4: =IF(ISNA(INDEX('Yardi Report'!$A:$E,MATCH('Chart of Accounts'!$A10,'Yardi Report'!$A:$A,0),1)),"",INDEX('Yardi Report'!$A:$E,MATCH('Chart of Accounts'!$A10,'Yardi Report'!$A:$A,0),1)) | B4: =IF(ISNA(INDEX('Yardi Report'!$A:$E,MATCH('Chart of Accounts'!$A10,'Yardi Report'!$A:$A,0),2)),"",INDEX('Yardi Report'!$A:$E,MATCH('Chart of Accounts'!$A10,'Yardi Report'!$A:$A,0),2)) | C4: =IF(A4="","",MAX($C$1:C3)+1) | E4: =A4&" "&B4 | G4: =+G3+1 | H4: =IF(ISNA(INDEX(C4:E503,MATCH(G4,C4:C503,0),3)),"",INDEX(C4:E503,MATCH(G4,C4:C503,0),3))
A5: =IF(ISNA(INDEX('Yardi Report'!$A:$E,MATCH('Chart of Accounts'!$A11,'Yardi Report'!$A:$A,0),1)),"",INDEX('Yardi Report'!$A:$E,MATCH('Chart of Accounts'!$A11,'Yardi Report'!$A:$A,0),1)) | B5: =IF(ISNA(INDEX('Yardi Report'!$A:$E,MATCH('Chart of Accounts'!$A11,'Yardi Report'!$A:$A,0),2)),"",INDEX('Yardi Report'!$A:$E,MATCH('Chart of Accounts'!$A11,'Yardi Report'!$A:$A,0),2)) | C5: =IF(A5="","",MAX($C$1:C4)+1) | E5: =A5&" "&B5 | G5: =+G4+1 | H5: =IF(ISNA(INDEX(C5:E504,MATCH(G5,C5:C504,0),3)),"",INDEX(C5:E504,MATCH(G5,C5:C504,0),3))
A6: =IF(ISNA(INDEX('Yardi Report'!$A:$E,MATCH('Chart of Accounts'!$A12,'Yardi Report'!$A:$A,0),1)),"",INDEX('Yardi Report'!$A:$E,MATCH('Chart of Accounts'!$A12,'Yardi Report'!$A:$A,0),1)) | B6: =IF(ISNA(INDEX('Yardi Report'!$A:$E,MATCH('Chart of Accounts'!$A12,'Yardi Report'!$A:$A,0),2)),"",INDEX('Yardi Report'!$A:$E,MATCH('Chart of Accounts'!$A12,'Yardi Report'!$A:$A,0),2)) | C6: =IF(A6="","",MAX($C$1:C5)+1) | E6: =A6&" "&B6 | G6: =+G5+1 | H6: =IF(ISNA(INDEX(C6:E505,MATCH(G6,C6:C505,0),3)),"",INDEX(C6:E505,MATCH(G6,C6:C505,0),3))
A7: =IF(ISNA(INDEX('Yardi Report'!$A:$E,MATCH('Chart of Accounts'!$A13,'Yardi Report'!$A:$A,0),1)),"",INDEX('Yardi Report'!$A:$E,MATCH('Chart of Accounts'!$A13,'Yardi Report'!$A:$A,0),1)) | B7: =IF(ISNA(INDEX('Yardi Report'!$A:$E,MATCH('Chart of Accounts'!$A13,'Yardi Report'!$A:$A,0),2)),"",INDEX('Yardi Report'!$A:$E,MATCH('Chart of Accounts'!$A13,'Yardi Report'!$A:$A,0),2)) | C7: =IF(A7="","",MAX($C$1:C6)+1) | E7: =A7&" "&B7 | G7: =+G6+1 | H7: =IF(ISNA(INDEX(C7:E506,MATCH(G7,C7:C506,0),3)),"",INDEX(C7:E506,MATCH(G7,C7:C506,0),3))
A8: =IF(ISNA(INDEX('Yardi Report'!$A:$E,MATCH('Chart of Accounts'!$A14,'Yardi Report'!$A:$A,0),1)),"",INDEX('Yardi Report'!$A:$E,MATCH('Chart of Accounts'!$A14,'Yardi Report'!$A:$A,0),1)) | B8: =IF(ISNA(INDEX('Yardi Report'!$A:$E,MATCH('Chart of Accounts'!$A14,'Yardi Report'!$A:$A,0),2)),"",INDEX('Yardi Report'!$A:$E,MATCH('Chart of Accounts'!$A14,'Yardi Report'!$A:$A,0),2)) | C8: =IF(A8="","",MAX($C$1:C7)+1) | E8: =A8&" "&B8 | G8: =+G7+1 | H8: =IF(ISNA(INDEX(C8:E507,MATCH(G8,C8:C507,0),3)),"",INDEX(C8:E507,MATCH(G8,C8:C507,0),3))
A9: =IF(ISNA(INDEX('Yardi Report'!$A:$E,MATCH('Chart of Accounts'!$A15,'Yardi Report'!$A:$A,0),1)),"",INDEX('Yardi Report'!$A:$E,MATCH('Chart of Accounts'!$A15,'Yardi Report'!$A:$A,0),1)) | B9: =IF(ISNA(INDEX('Yardi Report'!$A:$E,MATCH('Chart of Accounts'!$A15,'Yardi Report'!$A:$A,0),2)),"",INDEX('Yardi Report'!$A:$E,MATCH('Chart of Accounts'!$A15,'Yardi Report'!$A:$A,0),2)) | C9: =IF(A9="","",MAX($C$1:C8)+1) | E9: =A9&" "&B9 | G9: =+G8+1 | H9: =IF(ISNA(INDEX(C9:E508,MATCH(G9,C9:C508,0),3)),"",INDEX(C9:E508,MATCH(G9,C9:C508,0),3))
A10: =IF(ISNA(INDEX('Yardi Report'!$A:$E,MATCH('Chart of Accounts'!$A16,'Yardi Report'!$A:$A,0),1)),"",INDEX('Yardi Report'!$A:$E,MATCH('Chart of Accounts'!$A16,'Yardi Report'!$A:$A,0),1)) | B10: =IF(ISNA(INDEX('Yardi Report'!$A:$E,MATCH('Chart of Accounts'!$A16,'Yardi Report'!$A:$A,0),2)),"",INDEX('Yardi Report'!$A:$E,MATCH('Chart of Accounts'!$A16,'Yardi Report'!$A:$A,0),2)) | C10: =IF(A10="","",MAX($C$1:C9)+1) | E10: =A10&" "&B10 | G10: =+G9+1 | H10: =IF(ISNA(INDEX(C10:E509,MATCH(G10,C10:C509,0),3)),"",INDEX(C10:E509,MATCH(G10,C10:C509,0),3))
A11: =IF(ISNA(INDEX('Yardi Report'!$A:$E,MATCH('Chart of Accounts'!$A17,'Yardi Report'!$A:$A,0),1)),"",INDEX('Yardi Report'!$A:$E,MATCH('Chart of Accounts'!$A17,'Yardi Report'!$A:$A,0),1)) | B11: =IF(ISNA(INDEX('Yardi Report'!$A:$E,MATCH('Chart of Accounts'!$A17,'Yardi Report'!$A:$A,0),2)),"",INDEX('Yardi Report'!$A:$E,MATCH('Chart of Accounts'!$A17,'Yardi Report'!$A:$A,0),2)) | C11: =IF(A11="","",MAX($C$1:C10)+1) | E11: =A11&" "&B11 | G11: =+G10+1 | H11: =IF(ISNA(INDEX(C11:E510,MATCH(G11,C11:C510,0),3)),"",INDEX(C11:E510,MATCH(G11,C11:C510,0),3))
A12: =IF(ISNA(INDEX('Yardi Report'!$A:$E,MATCH('Chart of Accounts'!$A18,'Yardi Report'!$A:$A,0),1)),"",INDEX('Yardi Report'!$A:$E,MATCH('Chart of Accounts'!$A18,'Yardi Report'!$A:$A,0),1)) | B12: =IF(ISNA(INDEX('Yardi Report'!$A:$E,MATCH('Chart of Accounts'!$A18,'Yardi Report'!$A:$A,0),2)),"",INDEX('Yardi Report'!$A:$E,MATCH('Chart of Accounts'!$A18,'Yardi Report'!$A:$A,0),2)) | C12: =IF(A12="","",MAX($C$1:C11)+1) | E12: =A12&" "&B12 | G12: =+G11+1 | H12: =IF(ISNA(INDEX(C12:E511,MATCH(G12,C12:C511,0),3)),"",INDEX(C12:E511,MATCH(G12,C12:C511,0),3))
A13: =IF(ISNA(INDEX('Yardi Report'!$A:$E,MATCH('Chart of Accounts'!$A19,'Yardi Report'!$A:$A,0),1)),"",INDEX('Yardi Report'!$A:$E,MATCH('Chart of Accounts'!$A19,'Yardi Report'!$A:$A,0),1)) | B13: =IF(ISNA(INDEX('Yardi Report'!$A:$E,MATCH('Chart of Accounts'!$A19,'Yardi Report'!$A:$A,0),2)),"",INDEX('Yardi Report'!$A:$E,MATCH('Chart of Accounts'!$A19,'Yardi Report'!$A:$A,0),2)) | C13: =IF(A13="","",MAX($C$1:C12)+1) | E13: =A13&" "&B13 | G13: =+G12+1 | H13: =IF(ISNA(INDEX(C13:E512,MATCH(G13,C13:C512,0),3)),"",INDEX(C13:E512,MATCH(G13,C13:C512,0),3))
A14: =IF(ISNA(INDEX('Yardi Report'!$A:$E,MATCH('Chart of Accounts'!$A20,'Yardi Report'!$A:$A,0),1)),"",INDEX('Yardi Report'!$A:$E,MATCH('Chart of Accounts'!$A20,'Yardi Report'!$A:$A,0),1)) | B14: =IF(ISNA(INDEX('Yardi Report'!$A:$E,MATCH('Chart of Accounts'!$A20,'Yardi Report'!$A:$A,0),2)),"",INDEX('Yardi Report'!$A:$E,MATCH('Chart of Accounts'!$A20,'Yardi Report'!$A:$A,0),2)) | C14: =IF(A14="","",MAX($C$1:C13)+1) | E14: =A14&" "&B14 | G14: =+G13+1 | H14: =IF(ISNA(INDEX(C14:E513,MATCH(G14,C14:C513,0),3)),"",INDEX(C14:E513,MATCH(G14,C14:C513,0),3))
... A100: =IF(ISNA(INDEX('Yardi Report'!$A:$E,MATCH('Chart of Accounts'!$A106,'Yardi Report'!$A:$A,0),1)),"",INDEX('Yardi Report'!$A:$E,MATCH('Chart of Accounts'!$A106,'Yardi Report'!$A:$A,0),1)) | B100: =IF(ISNA(INDEX('Yardi Report'!$A:$E,MATCH('Chart of Accounts'!$A106,'Yardi Report'!$A:$A,0),2)),"",INDEX('Yardi Report'!$A:$E,MATCH('Chart of Accounts'!$A106,'Yardi Report'!$A:$A,0),2)) | C100: =IF(A100="","",MAX($C$1:C99)+1) | E100: =A100&" "&B100 | G100: =+G99+1 | H100: =IF(ISNA(INDEX(C100:E599,MATCH(G100,C100:C599,0),3)),"",INDEX(C100:E599,MATCH(G100,C100:C599,0),3))
A101: =IF(ISNA(INDEX('Yardi Report'!$A:$E,MATCH('Chart of Accounts'!$A107,'Yardi Report'!$A:$A,0),1)),"",INDEX('Yardi Report'!$A:$E,MATCH('Chart of Accounts'!$A107,'Yardi Report'!$A:$A,0),1)) | B101: =IF(ISNA(INDEX('Yardi Report'!$A:$E,MATCH('Chart of Accounts'!$A107,'Yardi Report'!$A:$A,0),2)),"",INDEX('Yardi Report'!$A:$E,MATCH('Chart of Accounts'!$A107,'Yardi Report'!$A:$A,0),2)) | C101: =IF(A101="","",MAX($C$1:C100)+1) | E101: =A101&" "&B101 | G101: =+G100+1
A102: =IF(ISNA(INDEX('Yardi Report'!$A:$E,MATCH('Chart of Accounts'!$A108,'Yardi Report'!$A:$A,0),1)),"",INDEX('Yardi Report'!$A:$E,MATCH('Chart of Accounts'!$A108,'Yardi Report'!$A:$A,0),1)) | B102: =IF(ISNA(INDEX('Yardi Report'!$A:$E,MATCH('Chart of Accounts'!$A108,'Yardi Report'!$A:$A,0),2)),"",INDEX('Yardi Report'!$A:$E,MATCH('Chart of Accounts'!$A108,'Yardi Report'!$A:$A,0),2)) | C102: =IF(A102="","",MAX($C$1:C101)+1) | E102: =A102&" "&B102 | G102: =+G101+1
A103: =IF(ISNA(INDEX('Yardi Report'!$A:$E,MATCH('Chart of Accounts'!$A109,'Yardi Report'!$A:$A,0),1)),"",INDEX('Yardi Report'!$A:$E,MATCH('Chart of Accounts'!$A109,'Yardi Report'!$A:$A,0),1)) | B103: =IF(ISNA(INDEX('Yardi Report'!$A:$E,MATCH('Chart of Accounts'!$A109,'Yardi Report'!$A:$A,0),2)),"",INDEX('Yardi Report'!$A:$E,MATCH('Chart of Accounts'!$A109,'Yardi Report'!$A:$A,0),2)) | C103: =IF(A103="","",MAX($C$1:C102)+1) | E103: =A103&" "&B103 | G103: =+G102+1
A104: =IF(ISNA(INDEX('Yardi Report'!$A:$E,MATCH('Chart of Accounts'!$A110,'Yardi Report'!$A:$A,0),1)),"",INDEX('Yardi Report'!$A:$E,MATCH('Chart of Accounts'!$A110,'Yardi Report'!$A:$A,0),1)) | B104: =IF(ISNA(INDEX('Yardi Report'!$A:$E,MATCH('Chart of Accounts'!$A110,'Yardi Report'!$A:$A,0),2)),"",INDEX('Yardi Report'!$A:$E,MATCH('Chart of Accounts'!$A110,'Yardi Report'!$A:$A,0),2)) | C104: =IF(A104="","",MAX($C$1:C103)+1) | E104: =A104&" "&B104 | G104: =+G103+1
A105: =IF(ISNA(INDEX('Yardi Report'!$A:$E,MATCH('Chart of Accounts'!$A111,'Yardi Report'!$A:$A,0),1)),"",INDEX('Yardi Report'!$A:$E,MATCH('Chart of Accounts'!$A111,'Yardi Report'!$A:$A,0),1)) | B105: =IF(ISNA(INDEX('Yardi Report'!$A:$E,MATCH('Chart of Accounts'!$A111,'Yardi Report'!$A:$A,0),2)),"",INDEX('Yardi Report'!$A:$E,MATCH('Chart of Accounts'!$A111,'Yardi Report'!$A:$A,0),2)) | C105: =IF(A105="","",MAX($C$1:C104)+1) | E105: =A105&" "&B105 | G105: =+G104+1
A106: =IF(ISNA(INDEX('Yardi Report'!$A:$E,MATCH('Chart of Accounts'!$A112,'Yardi Report'!$A:$A,0),1)),"",INDEX('Yardi Report'!$A:$E,MATCH('Chart of Accounts'!$A112,'Yardi Report'!$A:$A,0),1)) | B106: =IF(ISNA(INDEX('Yardi Report'!$A:$E,MATCH('Chart of Accounts'!$A112,'Yardi Report'!$A:$A,0),2)),"",INDEX('Yardi Report'!$A:$E,MATCH('Chart of Accounts'!$A112,'Yardi Report'!$A:$A,0),2)) | C106: =IF(A106="","",MAX($C$1:C105)+1) | E106: =A106&" "&B106 | G106: =+G105+1
A107: =IF(ISNA(INDEX('Yardi Report'!$A:$E,MATCH('Chart of Accounts'!$A113,'Yardi Report'!$A:$A,0),1)),"",INDEX('Yardi Report'!$A:$E,MATCH('Chart of Accounts'!$A113,'Yardi Report'!$A:$A,0),1)) | B107: =IF(ISNA(INDEX('Yardi Report'!$A:$E,MATCH('Chart of Accounts'!$A113,'Yardi Report'!$A:$A,0),2)),"",INDEX('Yardi Report'!$A:$E,MATCH('Chart of Accounts'!$A113,'Yardi Report'!$A:$A,0),2)) | C107: =IF(A107="","",MAX($C$1:C106)+1) | E107: =A107&" "&B107 | G107: =+G106+1
A108: =IF(ISNA(INDEX('Yardi Report'!$A:$E,MATCH('Chart of Accounts'!$A114,'Yardi Report'!$A:$A,0),1)),"",INDEX('Yardi Report'!$A:$E,MATCH('Chart of Accounts'!$A114,'Yardi Report'!$A:$A,0),1)) | B108: =IF(ISNA(INDEX('Yardi Report'!$A:$E,MATCH('Chart of Accounts'!$A114,'Yardi Report'!$A:$A,0),2)),"",INDEX('Yardi Report'!$A:$E,MATCH('Chart of Accounts'!$A114,'Yardi Report'!$A:$A,0),2)) | C108: =IF(A108="","",MAX($C$1:C107)+1) | E108: =A108&" "&B108 | G108: =+G107+1
A109: =IF(ISNA(INDEX('Yardi Report'!$A:$E,MATCH('Chart of Accounts'!$A115,'Yardi Report'!$A:$A,0),1)),"",INDEX('Yardi Report'!$A:$E,MATCH('Chart of Accounts'!$A115,'Yardi Report'!$A:$A,0),1)) | B109: =IF(ISNA(INDEX('Yardi Report'!$A:$E,MATCH('Chart of Accounts'!$A115,'Yardi Report'!$A:$A,0),2)),"",INDEX('Yardi Report'!$A:$E,MATCH('Chart of Accounts'!$A115,'Yardi Report'!$A:$A,0),2)) | C109: =IF(A109="","",MAX($C$1:C108)+1) | E109: =A109&" "&B109 | G109: =+G108+1
A110: =IF(ISNA(INDEX('Yardi Report'!$A:$E,MATCH('Chart of Accounts'!$A116,'Yardi Report'!$A:$A,0),1)),"",INDEX('Yardi Report'!$A:$E,MATCH('Chart of Accounts'!$A116,'Yardi Report'!$A:$A,0),1)) | B110: =IF(ISNA(INDEX('Yardi Report'!$A:$E,MATCH('Chart of Accounts'!$A116,'Yardi Report'!$A:$A,0),2)),"",INDEX('Yardi Report'!$A:$E,MATCH('Chart of Accounts'!$A116,'Yardi Report'!$A:$A,0),2)) | C110: =IF(A110="","",MAX($C$1:C109)+1) | E110: =A110&" "&B110 | G110: =+G109+1
A111: =IF(ISNA(INDEX('Yardi Report'!$A:$E,MATCH('Chart of Accounts'!$A117,'Yardi Report'!$A:$A,0),1)),"",INDEX('Yardi Report'!$A:$E,MATCH('Chart of Accounts'!$A117,'Yardi Report'!$A:$A,0),1)) | B111: =IF(ISNA(INDEX('Yardi Report'!$A:$E,MATCH('Chart of Accounts'!$A117,'Yardi Report'!$A:$A,0),2)),"",INDEX('Yardi Report'!$A:$E,MATCH('Chart of Accounts'!$A117,'Yardi Report'!$A:$A,0),2)) | C111: =IF(A111="","",MAX($C$1:C110)+1) | E111: =A111&" "&B111 | G111: =+G110+1
A112: =IF(ISNA(INDEX('Yardi Report'!$A:$E,MATCH('Chart of Accounts'!$A118,'Yardi Report'!$A:$A,0),1)),"",INDEX('Yardi Report'!$A:$E,MATCH('Chart of Accounts'!$A118,'Yardi Report'!$A:$A,0),1)) | B112: =IF(ISNA(INDEX('Yardi Report'!$A:$E,MATCH('Chart of Accounts'!$A118,'Yardi Report'!$A:$A,0),2)),"",INDEX('Yardi Report'!$A:$E,MATCH('Chart of Accounts'!$A118,'Yardi Report'!$A:$A,0),2)) | C112: =IF(A112="","",MAX($C$1:C111)+1) | E112: =A112&" "&B112 | G112: =+G111+1
... A467: =IF(ISNA(INDEX('Yardi Report'!$A:$E,MATCH('Chart of Accounts'!$A473,'Yardi Report'!$A:$A,0),1)),"",INDEX('Yardi Report'!$A:$E,MATCH('Chart of Accounts'!$A473,'Yardi Report'!$A:$A,0),1)) | B467: =IF(ISNA(INDEX('Yardi Report'!$A:$E,MATCH('Chart of Accounts'!$A473,'Yardi Report'!$A:$A,0),2)),"",INDEX('Yardi Report'!$A:$E,MATCH('Chart of Accounts'!$A473,'Yardi Report'!$A:$A,0),2)) | C467: =IF(A467="","",MAX($C$1:C466)+1) | E467: =A467&" "&B467 | G467: =+G466+1
